email_archiver/__init__.py
email_archiver/main.py
email_archiver/core/__init__.py
email_archiver/core/classifier.py
email_archiver/core/content_cleaner.py
email_archiver/core/db_handler.py
email_archiver/core/extractor.py
email_archiver/core/gmail_handler.py
email_archiver/core/graph_handler.py
email_archiver/core/llm_error_handler.py
email_archiver/core/paths.py
email_archiver/core/utils.py
email_archiver/server/app.py
email_archiver/server/nicegui_app.py
email_archiver/server/templates/index.html
email_archiver-1.4.4.dist-info/METADATA
email_archiver-1.4.4.dist-info/WHEEL
email_archiver-1.4.4.dist-info/entry_points.txt
email_archiver-1.4.4.dist-info/licenses/LICENSE
email_archiver-1.4.4.dist-info/RECORD
