Metadata-Version: 2.4
Name: email-archiver
Version: 1.4.4
Summary: Email-to-EML Secure Archiver
Project-URL: Homepage, https://realtimex.ai
Project-URL: Documentation, https://github.com/therealtimex/email-archiver/blob/main/docs/README.md
Project-URL: Repository, https://github.com/therealtimex/email-archiver
Project-URL: Issues, https://github.com/therealtimex/email-archiver/issues
Project-URL: Changelog, https://github.com/therealtimex/email-archiver/blob/main/CHANGELOG.md
Author-email: Trung Le <trung@realtimex.ai>
Maintainer: RealTimeX.ai Team
License-File: LICENSE
Keywords: archiver,backup,email,eml,gmail,microsoft365,webhook
Classifier: Development Status :: 4 - Beta
Classifier: Intended Audience :: Developers
Classifier: Intended Audience :: System Administrators
Classifier: License :: OSI Approved :: MIT License
Classifier: Operating System :: OS Independent
Classifier: Programming Language :: Python :: 3
Classifier: Programming Language :: Python :: 3.9
Classifier: Programming Language :: Python :: 3.10
Classifier: Programming Language :: Python :: 3.11
Classifier: Programming Language :: Python :: 3.12
Classifier: Topic :: Communications :: Email
Classifier: Topic :: System :: Archiving :: Backup
Requires-Python: >=3.9
Requires-Dist: fastapi
Requires-Dist: google-api-python-client
Requires-Dist: google-auth-oauthlib
Requires-Dist: jinja2
Requires-Dist: msal
Requires-Dist: nicegui>=3.4.1
Requires-Dist: openai>=1.0.0
Requires-Dist: python-dateutil
Requires-Dist: python-multipart
Requires-Dist: pyyaml
Requires-Dist: requests
Requires-Dist: tqdm
Requires-Dist: uvicorn
